domoji/__init__.py
domoji/__main__.py
domoji/lib.py
Domoji-1.1.1.dist-info/LICENSE
Domoji-1.1.1.dist-info/METADATA
Domoji-1.1.1.dist-info/WHEEL
Domoji-1.1.1.dist-info/entry_points.txt
Domoji-1.1.1.dist-info/top_level.txt
Domoji-1.1.1.dist-info/RECORD
