Metadata-Version: 2.1
Name: Domoji
Version: 1.1.1
Summary: Find Emoji Domains From The Command Line (Works on MacOS and Terminals That Accept Emojis
Home-page: https://github.com/M4cs/Domoji
Author: Max Bridgland
Author-email: mabridgland@protonmail.com
License: UNKNOWN
Keywords: domains,api,wrapper,emoji,emojicode,macOS
Platform: UNKNOWN
Classifier: Programming Language :: Python :: 3
Classifier: Programming Language :: Python :: 3.4
Classifier: Programming Language :: Python :: 3.5
Classifier: Programming Language :: Python :: 3.6
Classifier: Programming Language :: Python :: 3.7
Classifier: Topic :: Multimedia :: Graphics
Requires-Dist: requests (==2.21.0)
Requires-Dist: terminaltables (==3.1.0)
Requires-Dist: crayons (==0.2.0)
Requires-Dist: colorama (==0.4.1)
